taxfinder/__init__.py
taxfinder/taxfinder.py
taxfinder/update.py
taxfinder/db/taxinfo
taxfinder/db/taxinfo.p
taxfinder-0.0.1.dist-info/LICENSE
taxfinder-0.0.1.dist-info/METADATA
taxfinder-0.0.1.dist-info/WHEEL
taxfinder-0.0.1.dist-info/entry_points.txt
taxfinder-0.0.1.dist-info/top_level.txt
taxfinder-0.0.1.dist-info/RECORD
