Metadata-Version: 2.1
Name: taxfinder
Version: 0.0.1
Summary: Helper function to work with NCBI taxonomy ids
Home-page: https://github.com/MolecularBioinformatics/taxfinder
Author: Mathias Bockwoldt
Author-email: mathias.bockwoldt@gmail.com
Classifier: Programming Language :: Python :: 3 :: Only
Classifier: Programming Language :: Python :: 3.6
Classifier: Programming Language :: Python :: 3.7
Classifier: Programming Language :: Python :: 3.8
Classifier: Programming Language :: Python :: 3.9
Classifier: Programming Language :: Python :: 3.10
Classifier: License :: OSI Approved :: MIT License
Classifier: Operating System :: OS Independent
Classifier: Development Status :: 4 - Beta
Classifier: Intended Audience :: Science/Research
Classifier: Natural Language :: English
Classifier: Topic :: Scientific/Engineering :: Bio-Informatics
Requires-Python: >=3.6
License-File: LICENSE
